[
  {
    "input": "문장 생성: 나, 집, 가다",
    "output": "저는 집에 갑니다."
  },
  {
    "input": "문장 생성: 너, 이름, 무엇",
    "output": "당신의 이름은 무엇인가요?"
  },
  {
    "input": "문장 생성: 우리, 내일, 만나다",
    "output": "우리 내일 만나요."
  },
  {
    "input": "문장 생성: 오늘, 날씨, 좋다",
    "output": "오늘 날씨가 좋네요."
  },
  {
    "input": "문장 생성: 이거, 가격, 얼마",
    "output": "이것은 가격이 얼마예요?"
  },
  {
    "input": "문장 생성: 화장실, 어디",
    "output": "화장실이 어디에 있나요?"
  },
  {
    "input": "문장 생성: 배고프다, 밥, 먹다",
    "output": "배고픈데 밥 먹으러 가요."
  },
  {
    "input": "문장 생성: 만나다, 반갑다",
    "output": "만나서 반갑습니다."
  },
  {
    "input": "문장 생성: 고맙다, 감사하다",
    "output": "정말 고맙고 감사합니다."
  },
  {
    "input": "문장 생성: 미안하다, 죄송하다",
    "output": "정말 죄송합니다."
  },
  {
    "input": "문장 생성: 피곤하다, 자다, 가다",
    "output": "피곤해서 자러 가야겠어요."
  },
  {
    "input": "문장 생성: 영화, 보다, 재미있다",
    "output": "영화가 정말 재미있었어요."
  },
  {
    "input": "문장 생성: 공부, 하다, 어렵다",
    "output": "공부하는 것은 어렵습니다."
  },
  {
    "input": "문장 생성: 너, 좋아하다",
    "output": "저는 당신을 좋아해요."
  },
  {
    "input": "문장 생성: 괜찮다, 걱정, 아니다",
    "output": "괜찮아요, 걱정하지 마세요."
  },
  {
    "input": "문장 생성: 다시, 한번, 말하다, 부탁하다",
    "output": "다시 한번 말씀해 주시겠어요?"
  },
  {
    "input": "문장 생성: 병원, 가다, 아프다",
    "output": "몸이 아파서 병원에 가야 해요."
  },
  {
    "input": "문장 생성: 약속, 시간, 늦다",
    "output": "약속 시간에 늦을 것 같아요."
  },
  {
    "input": "문장 생성: 주말, 무엇, 하다",
    "output": "주말에 보통 무엇을 하세요?"
  },
  {
    "input": "문장 생성: 취미, 무엇",
    "output": "당신의 취미는 무엇인가요?"
  },
  {
    "input": "문장 생성: 커피, 마시다, 카페, 가다",
    "output": "커피 마시러 카페에 갈까요?"
  },
  {
    "input": "문장 생성: 돕다, 필요하다",
    "output": "도움이 필요하신가요?"
  },
  {
    "input": "문장 생성: 계산, 하다, 부탁하다",
    "output": "계산 부탁드립니다."
  },
  {
    "input": "문장 생성: 나, 수어, 배우다",
    "output": "저는 수어를 배우고 있어요."
  },
  {
    "input": "문장 생성: 이거, 어떻게, 사용하다",
    "output": "이것은 어떻게 사용하는 건가요?"
  },
  {
    "input": "문장 생성: 버스, 타다, 어디",
    "output": "버스는 어디서 타나요?"
  },
  {
    "input": "문장 생성: 책, 읽다, 좋아하다",
    "output": "저는 책 읽는 것을 좋아해요."
  },
  {
    "input": "문장 생성: 지금, 몇, 시",
    "output": "지금 몇 시예요?"
  },
  {
    "input": "문장 생성: 오늘, 무슨, 요일",
    "output": "오늘은 무슨 요일인가요?"
  },
  {
    "input": "문장 생성: 생일, 축하하다",
    "output": "생일을 진심으로 축하해요."
  },
  {
    "input": "문장 생성: 너, 너, 정말, 좋다",
    "output": "나는 네가 정말 좋아."
  },
  {
    "input": "문장 생성: 처음, 너, 만나다, 너, 처음",
    "output": "너를 처음 만났을 때가 생각나."
  },
  {
    "input": "문장 생성: 밥, 밥, 먹다, 가다",
    "output": "우리 밥 먹으러 가요."
  },
  {
    "input": "문장 생성: 어제, 친구, 만나다, 그리고, 영화, 보다",
    "output": "어제 친구를 만나서 영화를 봤어요."
  },
  {
    "input": "문장 생성: 나, 생각, 너, 생각, 같다",
    "output": "제 생각은 당신의 생각과 같아요."
  },
  {
    "input": "문장 생성: 왜, 너, 어제, 학교, 안 오다",
    "output": "어제 학교에 왜 안 왔어요?"
  },
  {
    "input": "문장 생성: 언제, 우리, 다시, 만나다",
    "output": "우리 언제 다시 만날 수 있을까요?"
  },
  {
    "input": "문장 생성: 어떻게, 이거, 만들다",
    "output": "이것은 어떻게 만들어요?"
  },
  {
    "input": "문장 생성: 누구, 오다",
    "output": "누가 오기로 했나요?"
  },
  {
    "input": "문장 생성: 무슨, 일",
    "output": "무슨 일 있어요?"
  },
  {
    "input": "문장 생성: 우리, 같이, 공부, 하다",
    "output": "우리 같이 공부해요."
  },
  {
    "input": "문장 생성: 조용히, 하다, 부탁하다",
    "output": "조용히 해주세요."
  },
  {
    "input": "문장 생성: 문, 닫다, 주다",
    "output": "문 좀 닫아주시겠어요?"
  },
  {
    "input": "문장 생성: 나, 돕다, 주다",
    "output": "저 좀 도와주세요."
  },
  {
    "input": "문장 생성: 걱정, 하다, 말다",
    "output": "걱정하지 마세요."
  },
  {
    "input": "문장 생성: 나, 오늘, 기분, 매우, 좋다",
    "output": "저 오늘 기분이 매우 좋아요."
  },
  {
    "input": "문장 생성: 머리, 아프다, 약, 필요하다",
    "output": "머리가 아파서 약이 필요해요."
  },
  {
    "input": "문장 생성: 너무, 슬프다, 울다",
    "output": "너무 슬퍼서 울고 싶어요."
  },
  {
    "input": "문장 생성: 깜짝, 놀라다",
    "output": "정말 깜짝 놀랐어요."
  },
  {
    "input": "문장 생성: 너, 보고 싶다",
    "output": "네가 보고 싶어."
  },
  {
    "input": "문장 생성: 전화번호, 알려주다, 수, 있다",
    "output": "전화번호를 알려주실 수 있나요?"
  },
  {
    "input": "문장 생성: 사진, 같이, 찍다",
    "output": "같이 사진 찍어요."
  },
  {
    "input": "문장 생성: 이, 근처, 맛집, 있다",
    "output": "이 근처에 맛집이 있나요?"
  },
  {
    "input": "문장 생성: 와이파이, 비밀번호, 무엇",
    "output": "와이파이 비밀번호가 뭐예요?"
  },
  {
    "input": "문장 생성: 길, 잃다, 같다",
    "output": "길을 잃어버린 것 같아요."
  },
  {
    "input": "문장 생성: 제일, 좋아하다, 음식, 무엇",
    "output": "가장 좋아하는 음식이 무엇인가요?"
  },
  {
    "input": "문장 생성: 맵다, 조금, 덜, 하다, 주다",
    "output": "조금 덜 맵게 해주세요."
  },
  {
    "input": "문장 생성: 늦다, 미안하다, 길, 막히다",
    "output": "늦어서 미안해요, 길이 많이 막혔어요."
  },
  {
    "input": "문장 생성: 이거, 나, 선물",
    "output": "이건 저를 위한 선물인가요?"
  },
  {
    "input": "문장 생성: 잘, 모르다",
    "output": "무슨 말인지 잘 모르겠어요."
  },
  {
    "input": "문장 생성: 천천히, 말하다, 주다",
    "output": "조금 더 천천히 말씀해 주세요."
  },
  {
    "input": "문장 생성: 한국, 처음, 오다",
    "output": "한국에는 처음 와봤어요."
  },
  {
    "input": "문장 생성: 오늘, 정말, 덥다",
    "output": "오늘 정말 덥네요."
  },
  {
    "input": "문장 생성: 비, 오다, 같다, 우산, 있다",
    "output": "비가 올 것 같은데, 우산 있어요?"
  },
  {
    "input": "문장 생성: 나, 생각, 다르다",
    "output": "제 생각은 조금 달라요."
  },
  {
    "input": "문장 생성: 잠, 부족하다, 졸리다",
    "output": "잠이 부족해서 너무 졸려요."
  },
  {
    "input": "문장 생성: 주소, 알려주다",
    "output": "정확한 주소를 알려주세요."
  },
  {
    "input": "문장 생성: 가방, 무겁다, 들다, 주다",
    "output": "가방이 무거운데 들어줄 수 있어요?"
  },
  {
    "input": "문장 생성: 이것, 진짜, 예쁘다",
    "output": "이거 진짜 예쁘네요."
  },
  {
    "input": "문장 생성: 너, 어제, 뭐, 하다",
    "output": "어제 뭐 했어요?"
  },
  {
    "input": "문장 생성: 나, 오늘, 약속, 있다",
    "output": "저는 오늘 약속이 있어요."
  },
  {
    "input": "문장 생성: 주말, 보통, 집, 있다",
    "output": "주말에는 보통 집에 있는 편이에요."
  },
  {
    "input": "문장 생성: 점심, 메뉴, 추천, 하다",
    "output": "점심 메뉴 좀 추천해 주세요."
  },
  {
    "input": "문장 생성: 요즘, 바쁘다, 지내다",
    "output": "요즘 어떻게 지내세요? 바쁘신가요?"
  },
  {
    "input": "문장 생성: 오랜만이다, 잘, 지내다",
    "output": "오랜만이에요, 잘 지냈어요?"
  },
  {
    "input": "문장 생성: 퇴근, 하다, 같이, 저녁, 먹다",
    "output": "퇴근하고 같이 저녁 먹을래요?"
  },
  {
    "input": "문장 생성: 날씨, 춥다, 옷, 따뜻하다, 입다",
    "output": "날씨가 추우니 옷 따뜻하게 입으세요."
  },
  {
    "input": "문장 생성: 잊다, 물건, 있다, 같다",
    "output": "잊어버리고 온 물건이 있는 것 같아요."
  },
  {
    "input": "문장 생성: 무슨, 음악, 듣다, 좋아하다",
    "output": "무슨 음악 듣는 거 좋아하세요?"
  },
  {
    "input": "문장 생성: 잠, 오다, 않다, 큰일",
    "output": "잠이 안 와서 큰일이에요."
  },
  {
    "input": "문장 생성: 오늘, 무슨, 좋은, 일, 있다",
    "output": "오늘 무슨 좋은 일 있었어요?"
  },
  {
    "input": "문장 생성: 나, 지금, 출발하다",
    "output": "저 지금 출발해요."
  },
  {
    "input": "문장 생성: 거의, 도착, 다, 하다",
    "output": "거의 다 도착했어요."
  },
  {
    "input": "문장 생성: 너, 닮다, 사람, 보다, 같다",
    "output": "당신을 닮은 사람을 본 것 같아요."
  },
  {
    "input": "문장 생성: 그, 소식, 듣다, 정말, 기쁘다",
    "output": "그 소식을 들으니 정말 기쁘네요."
  },
  {
    "input": "문장 생성: 시험, 떨어지다, 속상하다",
    "output": "시험에 떨어져서 너무 속상해요."
  },
  {
    "input": "문장 생성: 혼자, 있다, 심심하다",
    "output": "혼자 있으려니 심심하네요."
  },
  {
    "input": "문장 생성: 조금, 긴장, 되다",
    "output": "조금 긴장돼요."
  },
  {
    "input": "문장 생성: 웃다, 너무, 웃기다",
    "output": "너무 웃겨서 웃음이 멈추질 않아요."
  },
  {
    "input": "문장 생성: 스트레스, 받다, 풀다, 어떻게",
    "output": "스트레스 받을 때 어떻게 푸세요?"
  },
  {
    "input": "문장 생성: 그, 말, 듣다, 실망하다",
    "output": "그 말을 들으니 실망스러워요."
  },
  {
    "input": "문장 생성: 기대, 되다, 정말",
    "output": "정말 많이 기대돼요."
  },
  {
    "input": "문장 생성: 컨디션, 별로, 안, 좋다",
    "output": "오늘 컨디션이 별로 좋지 않아요."
  },
  {
    "input": "문장 생성: 무섭다, 영화, 보다, 못하다",
    "output": "저는 무서운 영화는 잘 못 봐요."
  },
  {
    "input": "문장 생성: 시간, 있다, 잠깐, 이야기, 하다",
    "output": "시간 괜찮으시면 잠깐 이야기 좀 할 수 있을까요?"
  },
  {
    "input": "문장 생성: 창문, 열다, 괜찮다",
    "output": "창문 좀 열어도 괜찮을까요?"
  },
  {
    "input": "문장 생성: 이거, 복사, 하다, 부탁하다",
    "output": "이것 좀 복사해 주세요."
  },
  {
    "input": "문장 생성: 내일, 아침, 일찍, 깨우다, 주다",
    "output": "내일 아침에 일찍 깨워줄 수 있어요?"
  },
  {
    "input": "문장 생성: 잠깐, 기다리다, 주다",
    "output": "잠깐만 기다려 주세요."
  },
  {
    "input": "문장 생성: 너무, 걱정, 않다",
    "output": "너무 걱정하지 않아도 돼요."
  },
  {
    "input": "문장 생성: 우리, 잠시, 쉬다, 가다",
    "output": "우리 잠시 쉬었다가 해요."
  },
  {
    "input": "문장 생성: 비밀, 지키다, 주다",
    "output": "비밀 지켜주세요."
  },
  {
    "input": "문장 생성: 이것, 어떻게, 생각하다",
    "output": "이것에 대해 어떻게 생각하세요?"
  },
  {
    "input": "문장 생성: 한번, 더, 기회, 주다",
    "output": "한 번만 더 기회를 주세요."
  },
  {
    "input": "문장 생성: 나, 그, 의견, 찬성하다",
    "output": "저는 그 의견에 찬성합니다."
  },
  {
    "input": "문장 생성: 아니다, 내, 생각, 다르다",
    "output": "아니요, 제 생각은 조금 다릅니다."
  },
  {
    "input": "문장 생성: 그, 방법, 좋다, 같다",
    "output": "그 방법이 더 좋을 것 같아요."
  },
  {
    "input": "문장 생성: 확실하다, 모르다",
    "output": "확실히는 잘 모르겠어요."
  },
  {
    "input": "문장 생성: 다시, 생각하다, 필요하다",
    "output": "다시 생각해 볼 필요가 있겠네요."
  },
  {
    "input": "문장 생성: 내, 말, 무슨, 뜻, 알다",
    "output": "제 말이 무슨 뜻인지 아시겠어요?"
  },
  {
    "input": "문장 생성: 그럴, 수, 있다, 생각하다",
    "output": "충분히 그럴 수 있다고 생각해요."
  },
  {
    "input": "문장 생성: 오해, 아니다, 주다, 좋다",
    "output": "오해하지 않았으면 좋겠어요."
  },
  {
    "input": "문장 생성: 내, 실수, 인정하다",
    "output": "제 실수라는 걸 인정합니다."
  },
  {
    "input": "문장 생성: 전혀, 생각, 못하다",
    "output": "전혀 생각지도 못한 일이에요."
  },
  {
    "input": "문장 생성: 이거, 입다, 보다, 수, 있다",
    "output": "이거 입어봐도 될까요?"
  },
  {
    "input": "문장 생성: 더, 크다, 사이즈, 있다",
    "output": "더 큰 사이즈 있나요?"
  },
  {
    "input": "문장 생성: 이거, 얼마",
    "output": "이건 얼마예요?"
  },
  {
    "input": "문장 생성: 카드, 계산, 되다",
    "output": "카드로 계산되나요?"
  },
  {
    "input": "문장 생성: 봉투, 필요하다, 없다",
    "output": "봉투는 필요 없어요."
  },
  {
    "input": "문장 생성: 아메리카노, 하나, 주다",
    "output": "아메리카노 한 잔 주세요."
  },
  {
    "input": "문장 생성: 포장, 하다, 가다",
    "output": "포장해갈게요."
  },
  {
    "input": "문장 생성: 여기서, 먹다, 가다",
    "output": "여기서 먹고 갈게요."
  },
  {
    "input": "문장 생성: 추천, 메뉴, 무엇",
    "output": "추천 메뉴가 무엇인가요?"
  },
  {
    "input": "문장 생성: 주문, 바꾸다, 수, 있다",
    "output": "주문을 바꿀 수 있을까요?"
  },
  {
    "input": "문장 생성: 이, 자리, 앉다, 되다",
    "output": "이 자리에 앉아도 되나요?"
  },
  {
    "input": "문장 생성: 물, 스스로, 가져오다",
    "output": "물은 셀프인가요?"
  },
  {
    "input": "문장 생성: 길, 건너다, 어떻게",
    "output": "길을 건너려면 어떻게 가야 하나요?"
  },
  {
    "input": "문장 생성: 여기서, 멀다",
    "output": "여기서 많이 먼가요?"
  },
  {
    "input": "문장 생성: 걸어서, 가다, 수, 있다",
    "output": "걸어서 갈 수 있는 거리인가요?"
  },
  {
    "input": "문장 생성: 배고프다, 그래서, 밥, 먹다",
    "output": "배가 고파서 밥을 먹으려고요."
  },
  {
    "input": "문장 생성: 비, 오다, 때문에, 약속, 취소되다",
    "output": "비가 오기 때문에 약속이 취소됐어요."
  },
  {
    "input": "문장 생성: 열심히, 공부하다, 하지만, 시험, 어렵다",
    "output": "열심히 공부했지만 시험은 어려웠어요."
  },
  {
    "input": "문장 생성: 시간, 없다, 그렇지만, 하다, 보다",
    "output": "시간은 없지만 한번 해 볼게요."
  },
  {
    "input": "문장 생성: 너, 오다, 그러면, 나, 가다",
    "output": "네가 온다면 나도 갈게."
  },
  {
    "input": "문장 생성: 피곤하다, 그리고, 졸리다",
    "output": "피곤하고 졸려요."
  },
  {
    "input": "문장 생성: 밥, 먹다, 그리고, 약, 먹다",
    "output": "밥을 먹고 나서 약을 먹어야 해요."
  },
  {
    "input": "문장 생성: 돈, 없다, 그러나, 사고 싶다",
    "output": "돈은 없지만 이건 정말 사고 싶다."
  },
  {
    "input": "문장 생성: 춥다, 또는, 덥다",
    "output": "춥거나 더운 것 중 어떤 걸 더 싫어해요?"
  },
  {
    "input": "문장 생성: 만약, 너, 라면, 어떻게, 하다",
    "output": "만약 당신이라면 어떻게 하시겠어요?"
  },
  {
    "input": "문장 생성: 나, 가다, 학교",
    "output": "저는 학교에 갑니다."
  },
  {
    "input": "문장 생성: 영화, 재미있다, 보다, 어제",
    "output": "어제 본 영화는 재미있었어요."
  },
  {
    "input": "문장 생성: 왜, 왜, 말, 안, 하다",
    "output": "왜 말을 안 해요?"
  },
  {
    "input": "문장 생성: 좋다, 그냥, 좋다",
    "output": "그냥 다 좋아요."
  },
  {
    "input": "문장 생성: 무엇, 무엇, 궁금하다",
    "output": "무엇이 궁금하세요?"
  },
  {
    "input": "문장 생성: 가다, 빨리, 빨리",
    "output": "빨리 가요!"
  },
  {
    "input": "문장 생성: 도착, 언제",
    "output": "언제 도착해요?"
  },
  {
    "input": "문장 생성: 먹다, 밥, 나",
    "output": "저는 밥을 먹었어요."
  },
  {
    "input": "문장 생성: 아니다, 아니다, 그, 아니다",
    "output": "아니에요, 그게 아니에요."
  },
  {
    "input": "문장 생성: 예쁘다, 정말, 예쁘다, 너",
    "output": "너 정말 예쁘다."
  },
  {
    "input": "문장 생성: 와이파이, 잘, 안, 되다",
    "output": "와이파이가 잘 안 터져요."
  },
  {
    "input": "문장 생성: 핸드폰, 배터리, 없다",
    "output": "핸드폰 배터리가 거의 없어요."
  },
  {
    "input": "문장 생성: 충전기, 빌리다, 수, 있다",
    "output": "충전기 좀 빌릴 수 있을까요?"
  },
  {
    "input": "문장 생성: 이거, 유통기한, 언제, 까지",
    "output": "이거 유통기한이 언제까지예요?"
  },
  {
    "input": "문장 생성: 알람, 못, 듣다, 늦잠, 자다",
    "output": "알람을 못 들어서 늦잠 잤어요."
  },
  {
    "input": "문장 생성: 엘리베이터, 어디, 있다",
    "output": "엘리베이터는 어디에 있나요?"
  },
  {
    "input": "문장 생성: 계단, 이용하다, 하다",
    "output": "계단을 이용해야 해요."
  },
  {
    "input": "문장 생성: 쓰레기, 어디, 버리다",
    "output": "쓰레기는 어디에 버려요?"
  },
  {
    "input": "문장 생성: 분리수거, 하다, 하다",
    "output": "분리수거를 해야 합니다."
  },
  {
    "input": "문장 생성: 오늘, 미세먼지, 심하다",
    "output": "오늘 미세먼지가 심하네요."
  },
  {
    "input": "문장 생성: 마스크, 쓰다, 하다",
    "output": "마스크를 쓰는 게 좋겠어요."
  },
  {
    "input": "문장 생성: 환기, 시키다, 필요하다",
    "output": "환기를 시킬 필요가 있어요."
  },
  {
    "input": "문장 생성: 택시, 잡다, 주다",
    "output": "택시 좀 불러주세요."
  },
  {
    "input": "문장 생성: 이, 주소, 가다, 주다",
    "output": "이 주소로 가주세요."
  },
  {
    "input": "문장 생성: 여기서, 세워주다",
    "output": "여기서 세워주세요."
  },
  {
    "input": "문장 생성: 잔돈, 괜찮다",
    "output": "잔돈은 괜찮아요."
  },
  {
    "input": "문장 생성: 유튜브, 보다, 시간, 가다",
    "output": "유튜브를 보다 보니 시간 가는 줄 몰랐어요."
  },
  {
    "input": "문장 생성: 구독, 좋아요, 부탁하다",
    "output": "구독과 좋아요 부탁드립니다."
  },
  {
    "input": "문장 생성: 다음, 영상, 기대하다, 주다",
    "output": "다음 영상도 기대해 주세요."
  },
  {
    "input": "문장 생성: 이, 노래, 제목, 무엇",
    "output": "이 노래 제목이 뭐예요?"
  },
  {
  "input": "문장 생성: 오늘, 날씨, 좋다",
  "output": "오늘 날씨가 좋습니다."
},
{
  "input": "문장 생성: 친구, 만나, 기쁘다",
  "output": "친구를 만나서 기뻐요."
},
{
  "input": "문장 생성: 지금, 시간, 얼마",
  "output": "지금 시간이 얼마인가요?"
},
{
  "input": "문장 생성: 밥, 먹다, 싶다",
  "output": "밥을 먹고 싶습니다."
},
{
  "input": "문장 생성: 학교, 가다, 늦다",
  "output": "학교에 늦게 갑니다."
},
{
  "input": "문장 생성: 선생님, 질문, 있다",
  "output": "선생님께 질문이 있습니다."
},
{
  "input": "문장 생성: 어제, 영화, 보다",
  "output": "어제 영화를 봤어요."
},
{
  "input": "문장 생성: 내일, 시험, 준비",
  "output": "내일 시험을 준비해야 합니다."
},
{
  "input": "문장 생성: 지금, 어디, 가다",
  "output": "지금 어디에 가시나요?"
},
{
  "input": "문장 생성: 나는, 피곤하다, 자다",
  "output": "저는 피곤해서 잠을 잡니다."
},
{
  "input": "문장 생성: 너, 책, 빌리다",
  "output": "너 책을 빌렸니?"
},
{
  "input": "문장 생성: 우리, 가족, 여행",
  "output": "우리 가족이 여행을 갑니다."
},
{
  "input": "문장 생성: 어머니, 요리, 맛있다",
  "output": "어머니 요리가 맛있습니다."
},
{
  "input": "문장 생성: 지금, 집, 없다",
  "output": "지금 집에 없습니다."
},
{
  "input": "문장 생성: 오늘, 점심, 같이",
  "output": "오늘 점심 같이 먹어요."
},
{
  "input": "문장 생성: 내일, 비, 오다",
  "output": "내일 비가 올 것 같습니다."
},
{
  "input": "문장 생성: 형, 운동, 좋아하다",
  "output": "형은 운동을 좋아합니다."
},
{
  "input": "문장 생성: 친구, 전화, 오다",
  "output": "친구한테서 전화가 왔어요."
},
{
  "input": "문장 생성: 나는, 책, 읽다",
  "output": "저는 책을 읽습니다."
},
{
  "input": "문장 생성: 지금, 공부, 하다",
  "output": "지금 공부하고 있어요."
},
{
  "input": "문장 생성: 너, 어디, 살다",
  "output": "너 어디에 살고 있니?"
},
{
  "input": "문장 생성: 오늘, 수업, 끝나다",
  "output": "오늘 수업이 끝났습니다."
},
{
  "input": "문장 생성: 내일, 같이, 점심",
  "output": "내일 같이 점심 먹을까요?"
},
{
  "input": "문장 생성: 지금, 날씨, 춥다",
  "output": "지금 날씨가 춥습니다."
},
{
  "input": "문장 생성: 나는, 음악, 듣다",
  "output": "저는 음악을 듣습니다."
},
{
  "input": "문장 생성: 오늘, 아침, 바쁘다",
  "output": "오늘 아침에 바빴습니다."
},
{
  "input": "문장 생성: 친구, 집, 방문",
  "output": "친구 집을 방문했어요."
},
{
  "input": "문장 생성: 우리, 내일, 공부",
  "output": "우리 내일 공부합시다."
},
{
  "input": "문장 생성: 아버지, 회사, 출근",
  "output": "아버지가 회사에 출근하셨어요."
},
{
  "input": "문장 생성: 나는, 운동, 하다",
  "output": "저는 운동을 합니다."
},
{
  "input": "문장 생성: 지금, 커피, 마시다",
  "output": "지금 커피를 마십니다."
},
{
  "input": "문장 생성: 내일, 약속, 있다",
  "output": "내일 약속이 있습니다."
},
{
  "input": "문장 생성: 오늘, 친구, 놀다",
  "output": "오늘 친구와 놀았습니다."
},
{
  "input": "문장 생성: 너, 무엇, 좋아하다",
  "output": "너는 무엇을 좋아하니?"
},
{
  "input": "문장 생성: 나는, 피아노, 치다",
  "output": "저는 피아노를 칩니다."
},
{
  "input": "문장 생성: 동생, 숙제, 하다",
  "output": "동생이 숙제를 하고 있어요."
},
{
  "input": "문장 생성: 오늘, 기분, 좋다",
  "output": "오늘 기분이 좋아요."
},
{
  "input": "문장 생성: 내일, 친구, 만나다",
  "output": "내일 친구를 만납니다."
},
{
  "input": "문장 생성: 나는, 영화관, 가다",
  "output": "저는 영화관에 갑니다."
},
{
  "input": "문장 생성: 지금, 책, 읽다",
  "output": "지금 책을 읽고 있어요."
},
{
  "input": "문장 생성: 오늘, 뉴스, 보다",
  "output": "오늘 뉴스를 봤습니다."
},
{
  "input": "문장 생성: 내일, 회사, 출근",
  "output": "내일 회사에 출근합니다."
},
{
  "input": "문장 생성: 나는, 여행, 가다",
  "output": "저는 여행을 갑니다."
},
{
  "input": "문장 생성: 친구, 생일, 축하",
  "output": "친구 생일을 축하합니다."
},
{
  "input": "문장 생성: 오늘, 병원, 가다",
  "output": "오늘 병원에 갔습니다."
},
{
  "input": "문장 생성: 너, 운동, 좋아하다",
  "output": "너는 운동을 좋아하니?"
},
{
  "input": "문장 생성: 지금, 배, 고프다",
  "output": "지금 배가 고픕니다."
},
{
  "input": "문장 생성: 내일, 여행, 가다",
  "output": "내일 여행을 갈 거예요."
},
{
  "input": "문장 생성: 오늘, 숙제, 끝내다",
  "output": "오늘 숙제를 끝냈습니다."
},
{
  "input": "문장 생성: 나는, 사진, 찍다",
  "output": "저는 사진을 찍습니다."
},
{
  "input": "문장 생성: 친구, 도움, 주다",
  "output": "친구가 도움을 줬습니다."
},
{
  "input": "문장 생성: 오늘, 집, 청소",
  "output": "오늘 집 청소를 했어요."
},
{
  "input": "문장 생성: 내일, 영화, 보다",
  "output": "내일 영화를 볼 예정입니다."
},
{
  "input": "문장 생성: 지금, 전화, 하다",
  "output": "지금 전화하고 있습니다."
},
{
  "input": "문장 생성: 오늘, 쇼핑, 가다",
  "output": "오늘 쇼핑을 갔습니다."
},
{
  "input": "문장 생성: 나는, 한국어, 배우다",
  "output": "저는 한국어를 배우고 있어요."
},
{
  "input": "문장 생성: 친구, 사진, 보내다",
  "output": "친구에게 사진을 보냈습니다."
},
{
  "input": "문장 생성: 오늘, 편지, 쓰다",
  "output": "오늘 편지를 썼습니다."
},
{
  "input": "문장 생성: 내일, 회의, 하다",
  "output": "내일 회의를 합니다."
},
{
  "input": "문장 생성: 나는, 버스, 타다",
  "output": "저는 버스를 탑니다."
},
{
  "input": "문장 생성: 친구, 노래, 부르다",
  "output": "친구가 노래를 불렀습니다."
},
{
  "input": "문장 생성: 오늘, 도서관, 가다",
  "output": "오늘 도서관에 갔습니다."
},
{
  "input": "문장 생성: 너, 어디, 있다",
  "output": "너는 어디에 있니?"
},
{
  "input": "문장 생성: 나는, 물, 마시다",
  "output": "저는 물을 마십니다."
},
{
  "input": "문장 생성: 오늘, 옷, 사다",
  "output": "오늘 옷을 샀습니다."
},
{
  "input": "문장 생성: 내일, 시험, 치다",
  "output": "내일 시험을 칩니다."
},
{
  "input": "문장 생성: 지금, 운동, 하다",
  "output": "지금 운동하고 있어요."
},
{
  "input": "문장 생성: 나는, 이메일, 보내다",
  "output": "저는 이메일을 보냈습니다."
},
{
  "input": "문장 생성: 오늘, 강의, 듣다",
  "output": "오늘 강의를 들었습니다."
},
{
  "input": "문장 생성: 내일, 친구, 집, 가다",
  "output": "내일 친구 집에 갑니다."
},
{
  "input": "문장 생성: 나는, 게임, 하다",
  "output": "저는 게임을 합니다."
},
{
  "input": "문장 생성: 지금, 공부, 시작",
  "output": "지금 공부를 시작합니다."
},
{
  "input": "문장 생성: 오늘, 피자, 먹다",
  "output": "오늘 피자를 먹었습니다."
},
{
  "input": "문장 생성: 내일, 바다, 놀다",
  "output": "내일 바다에서 놀 거예요."
},
{
  "input": "문장 생성: 나는, 책상, 정리",
  "output": "저는 책상을 정리했습니다."
},
{
  "input": "문장 생성: 친구, 선물, 받다",
  "output": "친구에게 선물을 받았습니다."
},
{
  "input": "문장 생성: 오늘, 길, 막히다",
  "output": "오늘 길이 막혔습니다."
},
{
  "input": "문장 생성: 내일, 학교, 없다",
  "output": "내일은 학교가 없습니다."
},
{
  "input": "문장 생성: 나는, 인터넷, 하다",
  "output": "저는 인터넷을 합니다."
},
{
  "input": "문장 생성: 지금, 음악, 듣다",
  "output": "지금 음악을 듣고 있어요."
},
{
  "input": "문장 생성: 오늘, 사진, 찍다",
  "output": "오늘 사진을 찍었습니다."
},
{
  "input": "문장 생성: 내일, 친구, 놀다",
  "output": "내일 친구와 놀 겁니다."
},
{
  "input": "문장 생성: 나는, 커피, 마시다",
  "output": "저는 커피를 마십니다."
},
{
  "input": "문장 생성: 지금, 메시지, 보내다",
  "output": "지금 메시지를 보냈습니다."
},
{
  "input": "문장 생성: 오늘, 집, 쉬다",
  "output": "오늘 집에서 쉬었습니다."
},
{
  "input": "문장 생성: 내일, 산책, 하다",
  "output": "내일 산책을 할 거예요."
},
{
  "input": "문장 생성: 나는, 과일, 먹다",
  "output": "저는 과일을 먹습니다."
},
{
  "input": "문장 생성: 친구, 이야기, 나누다",
  "output": "친구와 이야기를 나눴습니다."
},
{
  "input": "문장 생성: 오늘, 숙제, 하다",
  "output": "오늘 숙제를 했습니다."
},
{
  "input": "문장 생성: 내일, 집, 청소",
  "output": "내일 집을 청소할 예정입니다."
},
{
  "input": "문장 생성: 나는, 신문, 읽다",
  "output": "저는 신문을 읽습니다."
},
{
  "input": "문장 생성: 지금, 강아지, 산책",
  "output": "지금 강아지를 산책시키고 있어요."
},
{
  "input": "문장 생성: 오늘, 약속, 취소",
  "output": "오늘 약속이 취소되었습니다."
},
{
  "input": "문장 생성: 내일, 집, 방문",
  "output": "내일 집에 방문할 겁니다."
},
{
  "input": "문장 생성: 나는, 책, 사다",
  "output": "저는 책을 샀습니다."
},
{
  "input": "문장 생성: 친구, 집, 초대",
  "output": "친구 집에 초대받았습니다."
},
{
  "input": "문장 생성: 오늘, 길, 걷다",
  "output": "오늘 길을 걸었습니다."
},
{
  "input": "문장 생성: 내일, 비, 올까",
  "output": "내일 비가 올까요?"
},
{
  "input": "문장 생성: 나는, 지하철, 타다",
  "output": "저는 지하철을 탑니다."
},
{
  "input": "문장 생성: 지금, 책상, 앉다",
  "output": "지금 책상에 앉아 있습니다."
},
{
  "input": "문장 생성: 오늘, 친구, 전화",
  "output": "오늘 친구와 통화했습니다."
},
{
  "input": "문장 생성: 내일, 숙제, 많다",
  "output": "내일 숙제가 많습니다."
},
{
  "input": "문장 생성: 대학교, 수업, 듣다",
  "output": "대학교에서 수업을 듣습니다."
},
{
  "input": "문장 생성: 교수님, 강의, 재미있다",
  "output": "교수님 강의가 재미있어요."
},
{
  "input": "문장 생성: 대학교, 도서관, 공부",
  "output": "대학교 도서관에서 공부합니다."
},
{
  "input": "문장 생성: 이번주, 과제, 제출",
  "output": "이번 주에 과제를 제출해야 합니다."
},
{
  "input": "문장 생성: 동아리, 활동, 참여",
  "output": "동아리 활동에 참여했어요."
},
{
  "input": "문장 생성: 시험, 준비, 열심히",
  "output": "시험 준비를 열심히 하고 있습니다."
},
{
  "input": "문장 생성: 대학교, 친구, 사귀다",
  "output": "대학교에서 친구를 사귀었어요."
},
{
  "input": "문장 생성: 강의실, 자리, 없다",
  "output": "강의실에 자리가 없어요."
},
{
  "input": "문장 생성: 교수님, 질문, 하다",
  "output": "교수님께 질문을 했습니다."
},
{
  "input": "문장 생성: 수업, 발표, 준비",
  "output": "수업 발표를 준비하고 있어요."
},
{
  "input": "문장 생성: 도서관, 책, 빌리다",
  "output": "도서관에서 책을 빌렸습니다."
},
{
  "input": "문장 생성: 학식, 점심, 먹다",
  "output": "학식에서 점심을 먹었어요."
},
{
  "input": "문장 생성: 대학교, 시험, 치다",
  "output": "대학교에서 시험을 쳤습니다."
},
{
  "input": "문장 생성: 이번학기, 성적, 확인",
  "output": "이번 학기 성적을 확인했어요."
},
{
  "input": "문장 생성: 대학교, 축제, 즐기다",
  "output": "대학교 축제를 즐겼습니다."
},
{
  "input": "문장 생성: 과제, 마감, 다가오다",
  "output": "과제 마감이 다가오고 있습니다."
},
{
  "input": "문장 생성: 팀프로젝트, 회의, 진행",
  "output": "팀프로젝트 회의를 진행했어요."
},
{
  "input": "문장 생성: 조별과제, 힘들다, 많다",
  "output": "조별과제가 힘든 게 많습니다."
},
{
  "input": "문장 생성: 동기, 모임, 참석",
  "output": "동기 모임에 참석했습니다."
},
{
  "input": "문장 생성: 대학교, 전공, 공부",
  "output": "대학교에서 전공을 공부합니다."
},
{
  "input": "문장 생성: 졸업, 준비, 하다",
  "output": "졸업 준비를 하고 있어요."
},
{
  "input": "문장 생성: 대학교, 시험기간, 바쁘다",
  "output": "대학교 시험기간이라 바쁩니다."
},
{
  "input": "문장 생성: 강의실, 이동, 늦다",
  "output": "강의실로 이동하느라 늦었어요."
},
{
  "input": "문장 생성: 동아리, 친구, 많다",
  "output": "동아리에서 친구가 많습니다."
},
{
  "input": "문장 생성: 대학교, 기숙사, 생활",
  "output": "대학교 기숙사에서 생활합니다."
},
{
  "input": "문장 생성: 교수님, 과제, 안내",
  "output": "교수님이 과제를 안내해 주셨습니다."
},
{
  "input": "문장 생성: 전공, 수업, 어렵다",
  "output": "전공 수업이 어렵습니다."
},
{
  "input": "문장 생성: 동기, 시험, 공부",
  "output": "동기와 함께 시험 공부했어요."
},
{
  "input": "문장 생성: 강의, 지각, 하다",
  "output": "강의에 지각했습니다."
},
{
  "input": "문장 생성: 대학교, 졸업식, 열리다",
  "output": "대학교 졸업식이 열렸습니다."
},
{
  "input": "문장 생성: 조별과제, 발표, 준비",
  "output": "조별과제 발표를 준비하고 있습니다."
},
{
  "input": "문장 생성: 대학원, 진학, 고민",
  "output": "대학원 진학을 고민하고 있어요."
},
{
  "input": "문장 생성: 동아리, 회장, 선출",
  "output": "동아리 회장을 선출했습니다."
},
{
  "input": "문장 생성: 대학교, 등록금, 내다",
  "output": "대학교 등록금을 냈습니다."
},
{
  "input": "문장 생성: 이번학기, 휴학, 신청",
  "output": "이번 학기에 휴학을 신청했습니다."
},
{
  "input": "문장 생성: 전공, 교수님, 상담",
  "output": "전공 교수님과 상담했습니다."
},
{
  "input": "문장 생성: 동아리방, 친구, 모이다",
  "output": "동아리방에 친구들이 모였습니다."
},
{
  "input": "문장 생성: 대학교, 신입생, 환영회",
  "output": "대학교 신입생 환영회가 열렸습니다."
},
{
  "input": "문장 생성: 과제, 발표, 끝나다",
  "output": "과제 발표가 끝났습니다."
},
{
  "input": "문장 생성: 대학교, 캠퍼스, 산책",
  "output": "대학교 캠퍼스를 산책했어요."
},
{
  "input": "문장 생성: 이번학기, 수강신청, 완료",
  "output": "이번 학기 수강신청을 완료했습니다."
},
{
  "input": "문장 생성: 교수님, 시험문제, 내다",
  "output": "교수님이 시험 문제를 내셨습니다."
},
{
  "input": "문장 생성: 강의, 결석, 많다",
  "output": "강의 결석이 많습니다."
},
{
  "input": "문장 생성: 대학교, 동아리, 모임",
  "output": "대학교 동아리 모임이 있었습니다."
},
{
  "input": "문장 생성: 도서관, 자리, 부족하다",
  "output": "도서관에 자리가 부족합니다."
},
{
  "input": "문장 생성: 동기, 밥, 먹다",
  "output": "동기와 밥을 먹었습니다."
},
{
  "input": "문장 생성: 이번주, 리포트, 쓰다",
  "output": "이번 주에 리포트를 썼습니다."
},
{
  "input": "문장 생성: 대학교, 학점, 관리",
  "output": "대학교에서 학점을 관리해야 합니다."
},
{
  "input": "문장 생성: 졸업, 요건, 충족",
  "output": "졸업 요건을 충족했습니다."
},
{
  "input": "문장 생성: 동아리, 활동, 재미있다",
  "output": "동아리 활동이 재미있습니다."
},
{
  "input": "문장 생성: 오늘, 날씨, 좋다",
  "output": "오늘 날씨가 좋습니다."
},
{
  "input": "문장 생성: 내일, 시험, 준비, 하다",
  "output": "내일 시험 준비를 해야 합니다."
},
{
  "input": "문장 생성: 친구, 만나, 커피, 마시다",
  "output": "친구를 만나서 커피를 마셨어요."
},
{
  "input": "문장 생성: 집, 청소, 하다, 피곤하다, 쉬다",
  "output": "집 청소를 하고 피곤해서 쉬었습니다."
},
{
  "input": "문장 생성: 아침, 늦잠, 자다, 수업, 지각, 하다",
  "output": "아침에 늦잠을 자서 수업에 지각했습니다."
},
{
  "input": "문장 생성: 오늘, 저녁, 먹다, 무엇",
  "output": "오늘 저녁에 무엇을 먹을까요?"
},
{
  "input": "문장 생성: 여행, 준비, 하다, 짐, 싸다",
  "output": "여행 준비를 하느라 짐을 쌌습니다."
},
{
  "input": "문장 생성: 동아리, 활동, 하다, 즐겁다",
  "output": "동아리 활동을 해서 즐거웠습니다."
},
{
  "input": "문장 생성: 나는, 피곤하다, 공부, 끝내다",
  "output": "저는 피곤하지만 공부를 끝냈습니다."
},
{
  "input": "문장 생성: 오늘, 도서관, 가다, 시험, 공부, 하다",
  "output": "오늘 도서관에 가서 시험 공부를 했습니다."
},
{
  "input": "문장 생성: 내일, 가족, 여행, 가다, 바다, 놀다",
  "output": "내일 가족과 함께 바다에 여행 가서 놀 겁니다."
},
{
  "input": "문장 생성: 친구, 집, 초대, 받다, 저녁, 먹다",
  "output": "친구 집에 초대받아 저녁을 먹었습니다."
},
{
  "input": "문장 생성: 나는, 오늘, 영화관, 가다, 영화, 보다",
  "output": "저는 오늘 영화관에 가서 영화를 봤습니다."
},
{
  "input": "문장 생성: 아침, 버스, 타다, 길, 막히다, 늦다",
  "output": "아침에 버스를 탔는데 길이 막혀 늦었습니다."
},
{
  "input": "문장 생성: 이번주, 리포트, 쓰다, 발표, 준비, 하다",
  "output": "이번 주에 리포트를 쓰고 발표 준비를 했습니다."
},
{
  "input": "문장 생성: 오늘, 비, 오다, 우산, 없다",
  "output": "오늘 비가 오는데 우산이 없었습니다."
},
{
  "input": "문장 생성: 나는, 내일, 친구, 만나, 식당, 예약, 하다",
  "output": "저는 내일 친구를 만나기 위해 식당을 예약했습니다."
},
{
  "input": "문장 생성: 방학, 아르바이트, 시작, 하다, 돈, 모으다",
  "output": "방학에 아르바이트를 시작해서 돈을 모았습니다."
},
{
  "input": "문장 생성: 친구, 전화, 오다, 약속, 취소, 하다",
  "output": "친구에게서 전화가 와서 약속을 취소했습니다."
},
{
  "input": "문장 생성: 이번학기, 수업, 듣다, 과제, 많다",
  "output": "이번 학기에 수업을 들으면서 과제가 많았습니다."
},
{
  "input": "문장 생성: 어제, 새벽, 늦게, 자다, 피곤하다",
  "output": "어제 새벽에 늦게 자서 피곤합니다."
},
{
  "input": "문장 생성: 나는, 오늘, 지하철, 타다, 지연, 늦다",
  "output": "저는 오늘 지하철을 탔는데 지연돼서 늦었습니다."
},
{
  "input": "문장 생성: 친구, 기숙사, 가다, 놀다",
  "output": "친구 기숙사에 가서 놀았습니다."
},
{
  "input": "문장 생성: 오늘, 수업, 발표, 준비, 하다, 잘되다",
  "output": "오늘 수업 발표 준비가 잘 되었습니다."
},
{
  "input": "문장 생성: 내일, 시험, 치다, 도서관, 공부, 하다",
  "output": "내일 시험을 치기 위해 도서관에서 공부했습니다."
},
{
  "input": "문장 생성: 아버지, 회사, 다니다, 바쁘다, 늦다",
  "output": "아버지가 회사 다니시느라 바빠서 늦으셨어요."
},
{
  "input": "문장 생성: 오늘, 저녁, 피자, 먹다, 치킨, 먹다",
  "output": "오늘 저녁에 피자와 치킨을 먹었습니다."
},
{
  "input": "문장 생성: 나는, 어제, 기분, 좋다, 친구, 웃다",
  "output": "저는 어제 기분이 좋아서 친구와 웃었습니다."
},
{
  "input": "문장 생성: 여행, 계획, 세우다, 비행기, 예약, 하다",
  "output": "여행 계획을 세우고 비행기를 예약했습니다."
},
{
  "input": "문장 생성: 오늘, 동아리, 모임, 하다, 발표, 준비, 하다",
  "output": "오늘 동아리 모임에서 발표 준비를 했습니다."
},
{
  "input": "문장 생성: 내일, 아침, 일찍, 일어나다, 준비, 하다",
  "output": "내일 아침에 일찍 일어나 준비해야 합니다."
},
{
  "input": "문장 생성: 오늘, 도서관, 가다, 사람, 많다, 자리, 없다",
  "output": "오늘 도서관에 갔는데 사람이 많아 자리가 없었습니다."
},
{
  "input": "문장 생성: 친구, 졸업, 하다, 선물, 주다",
  "output": "친구가 졸업해서 선물을 주었습니다."
},
{
  "input": "문장 생성: 나는, 내일, 동아리, 공연, 있다, 기대, 하다",
  "output": "저는 내일 동아리 공연이 있어 기대하고 있습니다."
},
{
  "input": "문장 생성: 이번주, 날씨, 덥다, 시원하다, 원하다",
  "output": "이번 주 날씨가 더워서 시원해지길 원합니다."
},
{
  "input": "문장 생성: 어머니, 요리, 하다, 점심, 먹다, 맛있다",
  "output": "어머니가 요리해 주신 점심을 먹었는데 맛있었습니다."
},
{
  "input": "문장 생성: 오늘, 학교, 도착, 하다, 바로, 시험, 치다",
  "output": "오늘 학교에 도착하자마자 바로 시험을 쳤습니다."
},
{
  "input": "문장 생성: 나는, 내일, 발표, 하다, 자료, 부족하다, 걱정",
  "output": "저는 내일 발표할 자료가 부족해서 걱정입니다."
},
{
  "input": "문장 생성: 친구, 여행, 가다, 사진, 보내다",
  "output": "친구가 여행을 가서 사진을 보냈습니다."
},
{
  "input": "문장 생성: 이번주, 영화, 보다, 친구, 즐겁다",
  "output": "이번 주에 친구와 영화를 봐서 즐거웠습니다."
},
{
  "input": "문장 생성: 오늘, 버스, 타다, 길, 막히다, 지각, 하다",
  "output": "오늘 버스를 탔는데 길이 막혀 지각했습니다."
},
{
  "input": "문장 생성: 나는, 이번학기, 성적, 관리, 하다, 신경쓰다",
  "output": "저는 이번 학기 성적 관리에 신경 쓰고 있습니다."
},
{
  "input": "문장 생성: 내일, 기숙사, 청소, 하다, 검사, 준비, 하다",
  "output": "내일 기숙사 청소 검사가 있어 준비했습니다."
},
{
  "input": "문장 생성: 친구, 약속, 하다, 갑자기, 취소, 되다",
  "output": "친구와 약속을 했는데 갑자기 취소되었습니다."
},
{
  "input": "문장 생성: 오늘, 저녁, 영화, 보다, 늦다, 귀가, 하다",
  "output": "오늘 저녁에 영화를 보고 늦게 귀가했습니다."
},
{
  "input": "문장 생성: 나는, 내일, 동아리, 모임, 있다, 기대, 하다",
  "output": "저는 내일 동아리 모임이 있어 기대하고 있습니다."
},
{
  "input": "문장 생성: 이번주, 리포트, 쓰다, 제출, 하다, 서두르다",
  "output": "이번 주 리포트를 쓰고 제출하느라 서둘렀습니다."
},
{
  "input": "문장 생성: 아침, 운동, 하다, 기분, 상쾌하다",
  "output": "아침에 운동을 하니 기분이 상쾌합니다."
},
{
  "input": "문장 생성: 나는, 어제, 친구, 만나다, 이야기, 나누다, 웃다",
  "output": "저는 어제 친구를 만나 이야기 나누며 웃었습니다."
},
{
  "input": "문장 생성: 오늘, 학교, 도서관, 가다, 공부, 오래, 하다",
  "output": "오늘 학교 도서관에 가서 공부를 오래 했습니다."
}
]
